cellotype/__init__.py
cellotype/dataset.py
cellotype/evaluate.py
cellotype/predict.py
cellotype/trainer.py
cellotype/visualize.py
cellotype/maskdino/__init__.py
cellotype/maskdino/config.py
cellotype/maskdino/maskdino.py
cellotype/maskdino/test_time_augmentation.py
cellotype/maskdino/data/__init__.py
cellotype/maskdino/data/dataset_mappers/__init__.py
cellotype/maskdino/data/dataset_mappers/coco_instance_new_baseline_dataset_mapper.py
cellotype/maskdino/data/dataset_mappers/coco_panoptic_new_baseline_dataset_mapper.py
cellotype/maskdino/data/dataset_mappers/codex_mapper.py
cellotype/maskdino/data/dataset_mappers/detr_dataset_mapper.py
cellotype/maskdino/data/dataset_mappers/mask_former_semantic_dataset_mapper.py
cellotype/maskdino/data/datasets/__init__.py
cellotype/maskdino/data/datasets/register_ade20k_full.py
cellotype/maskdino/data/datasets/register_ade20k_instance.py
cellotype/maskdino/data/datasets/register_ade20k_panoptic.py
cellotype/maskdino/data/datasets/register_coco_panoptic_annos_semseg.py
cellotype/maskdino/data/datasets/register_coco_stuff_10k.py
cellotype/maskdino/data/datasets/register_mapillary_vistas.py
cellotype/maskdino/data/datasets/register_mapillary_vistas_panoptic.py
cellotype/maskdino/evaluation/__init__.py
cellotype/maskdino/evaluation/instance_evaluation.py
cellotype/maskdino/modeling/__init__.py
cellotype/maskdino/modeling/criterion.py
cellotype/maskdino/modeling/matcher.py
cellotype/maskdino/modeling/backbone/__init__.py
cellotype/maskdino/modeling/backbone/focal.py
cellotype/maskdino/modeling/backbone/swin.py
cellotype/maskdino/modeling/meta_arch/__init__.py
cellotype/maskdino/modeling/meta_arch/maskdino_head.py
cellotype/maskdino/modeling/pixel_decoder/__init__.py
cellotype/maskdino/modeling/pixel_decoder/maskdino_encoder.py
cellotype/maskdino/modeling/pixel_decoder/position_encoding.py
cellotype/maskdino/modeling/transformer_decoder/__init__.py
cellotype/maskdino/modeling/transformer_decoder/dino_decoder.py
cellotype-0.1.dist-info/LICENSE
cellotype-0.1.dist-info/METADATA
cellotype-0.1.dist-info/WHEEL
cellotype-0.1.dist-info/top_level.txt
cellotype-0.1.dist-info/RECORD
